langgraph_checkpoint_firestore/LICENSE
langgraph_checkpoint_firestore/__init__.py
langgraph_checkpoint_firestore/firestoreSaver.py
langgraph_checkpoint_firestore/firestoreSerializer.py
langgraph_checkpoint_firestore/test.py
langgraph_checkpoint_firestore-0.1.7.dist-info/METADATA
langgraph_checkpoint_firestore-0.1.7.dist-info/WHEEL
langgraph_checkpoint_firestore-0.1.7.dist-info/RECORD
